gabia_sms/__init__.py
gabia_sms/codes.py
gabia_sms/core.py
gabia_sms/exceptions.py
gabia_sms/formats.py
gabia_sms/parser.py
gabia_sms/shortcuts.py
gabia_sms/utils.py
gabia_sms_Django-1.2.1.dist-info/DESCRIPTION.rst
gabia_sms_Django-1.2.1.dist-info/METADATA
gabia_sms_Django-1.2.1.dist-info/RECORD
gabia_sms_Django-1.2.1.dist-info/WHEEL
gabia_sms_Django-1.2.1.dist-info/metadata.json
gabia_sms_Django-1.2.1.dist-info/top_level.txt
