Metadata-Version: 2.0
Name: gabia-sms-Django
Version: 1.2.1
Summary: Send SMS messages to mobile devices through GABIA SMS api.
Home-page: https://github.com/hwshim0810/gabia-sms-Django
Author: Hyunwoo Shim
Author-email: hyunwoo.shim@laziness.xyz
License: UNKNOWN
Download-URL: https://github.com/hwshim0810/gabia-sms-Django/archive/master.zip
Platform: UNKNOWN
Classifier: Intended Audience :: Developers
Classifier: Operating System :: OS Independent
Classifier: License :: OSI Approved :: Apache Software License
Classifier: Programming Language :: Python
Classifier: Programming Language :: Python :: 2
Classifier: Programming Language :: Python :: 2.7
Classifier: Programming Language :: Python :: 3
Classifier: Programming Language :: Python :: 3.4
Classifier: Programming Language :: Python :: 3.5
Classifier: Programming Language :: Python :: 3.6
Requires-Dist: Django (>=1.11)
